autoselenium/__init__.py
autoselenium/resources/add_render.js
autoselenium-1.0.0.dist-info/LICENSE
autoselenium-1.0.0.dist-info/METADATA
autoselenium-1.0.0.dist-info/WHEEL
autoselenium-1.0.0.dist-info/top_level.txt
autoselenium-1.0.0.dist-info/RECORD
