Metadata-Version: 2.1
Name: autoselenium
Version: 1.0.0
Summary: Ready-to-run Selenium.
Home-page: https://github.com/juancroldan/autoselenium
Author: J. Carlos Roldán
Author-email: juancarlos@sevilla.es
Classifier: Development Status :: 5 - Production/Stable
Classifier: Intended Audience :: Developers
Classifier: Natural Language :: English
Classifier: Programming Language :: Python :: 3
Classifier: Operating System :: OS Independent
License-File: LICENSE
Requires-Dist: requests
Requires-Dist: selenium
Requires-Dist: tqdm
